wifi_password
