Metadata-Version: 2.1
Name: wifi-password
Version: 1.1.0
Summary: Quickly fetch your WiFi password and if needed, generate a QR code of your WiFi to allow phones to easily connect
Home-page: https://github.com/sdushantha/wifi-password
Author: Siddharth Dushantha
Author-email: siddharth.dushantha@gmail.com
License: UNKNOWN
Platform: UNKNOWN
